Workbook

Sheet Lista de Chequeo Q5
A1: SENA - REGIONAL ANTIOQUIA | CENTRO DE SERVICIO Y GESTIÓN EMPRESARIAL
A2: LISTA DE CHEQUEO - QUINTO AVANCE: REACT + VITE + FASTAPI + BASE DE DATOS SQL + INTELIGENCIA ARTIFICIAL
A4: 1. DATOS DEL APRENDIZ Y DEL PROGRAMA DE FORMACIÓN
A5: Nombre del Aprendiz: | B5: Tomas Cardona Hincapie | D5: Fecha de Presentación: | F5: 2026-09-14
A6: Documento de Identidad: | B6: TI 1025654102 | D6: Ficha de Caracterización: | F6: 3406211
A7: Programa de Formación: | B7: ADSO (Análisis y Desarrollo de Software) | D7: Trimestre / Ambiente: | F7: 03 / Ambiente
A8: Competencia: | B8: React + Vite / FastAPI | D8: Instructor Lider: | F8: Jhan Hader Muñoz
A9: 2. INDICADORES DE AVANCE Y RESUMEN DE EVALUACIÓN
A10: Total Requerimientos: | B10: =COUNTA(A15:A39) | C10: Requerimientos Cumplidos: | D10: =COUNTIF(E14:E39, "Cumplido") | E10: % de Avance del Proyecto: | F10: =D10/B10
A11: Requerimientos En Proceso: | B11: =COUNTIF(E14:E39, "En Proceso") | C11: Requerimientos Pendientes: | D11: =COUNTIF(E14:E39, "Pendiente") | E11: Estado de Avance: | F11: =IF(F10>=1, "COMPLETADO", IF(F10>0, "EN PROCESO", "PENDIENTE REVISIÓN"))
A12: Valoración Final Instructor: | B12: Aprobado / No Aprobado
A13: 3. LISTA DE CHEQUEO - REQUERIMIENTOS DETALLADOS DEL ENTREGABLE (REQ-01 AL REQ-26)
A14: No. | B14: Categoría / Módulo | C14: Requerimiento | D14: Detalle / Criterio de Aceptación (PDF Quinto Avance) | E14: Estado | F14: Espacio para Evidencia / Captura de Pantalla | G14: Observaciones del Aprendiz / Notas de Entrega
A15: REQ-01 | B15: Módulo de Ventas | C15: Módulo de ventas | D15: El sistema deberá permitir registrar las ventas realizadas desde el sitio web, relacionando cliente, usuario operador, productos/servicios vendidos, cantidades, precios, descuentos, subtotal, impuestos, total, fecha/hora y estado, almacenado de manera persistente en BD SQL. | E15: Cumplido | F15: [Pegar Captura de Pantalla Aquí] | G15: POST /api/ventas registra la venta con cliente, vendedor, productos, servicios, cantidades, descuentos, subtotal, IVA del 19%, total, forma de pago, fecha y estado. Los precios se leen del catalogo, nunca de la peticion. Descuenta inventario y anular lo devuelve. Se puede registrar desde el panel o desde el carrito del sitio.
A16: REQ-02 | B16: Módulo de Ventas | C16: Registro de productos y servicios vendidos | D16: El sistema deberá identificar productos y servicios incluidos en cada venta con relación detalle-venta, permitiendo almacenar cantidades, precios y valores correspondientes a cada elemento comercializado. | E16: Cumplido | F16: [Pegar Captura de Pantalla Aquí] | G16: Tabla detalle_ventas: una fila por articulo con tipo (producto o servicio), cantidad, precio unitario, descuento y subtotal. Guarda copia del nombre y del precio del momento, asi el historico no cambia si el articulo se edita o se retira del catalogo.
A17: REQ-03 | B17: Módulo de Ventas | C17: Historial de ventas | D17: Módulo para consultar el historial de ventas registradas con criterios de búsqueda/filtrado por fecha, cliente, producto, servicio, estado y valor de la venta. | E17: Cumplido | F17: [Pegar Captura de Pantalla Aquí] | G17: GET /api/ventas filtra por fecha inicial y final, cliente, producto, servicio, estado, forma de pago, valor minimo y maximo, y texto libre sobre numero de venta, nombre, correo o documento. El cliente solo recibe sus propias compras.
A18: REQ-04 | B18: Reportes y Facturación | C18: Reporte diario de ventas | D18: Generar reporte diario de ventas con la información registrada en una fecha determinada, incluyendo fecha, número de venta, cliente, productos/servicios, cantidad, valor, total y estado. | E18: Cumplido | F18: [Pegar Captura de Pantalla Aquí] | G18: GET /api/reportes/ventas-diarias devuelve fecha, numero de venta, cliente, productos y servicios, cantidad, valor, total y estado. Los tres formatos (pantalla, PDF y Excel) salen de un unico calculo, para que no puedan discrepar entre si.
A19: REQ-05 | B19: Reportes y Facturación | C19: Exportación del reporte en PDF | D19: Implementar la generación del reporte diario de ventas en formato PDF estructurado con nombre/ID de proyecto, fecha, información de ventas, totales y datos de generación. | E19: Cumplido | F19: [Pegar Captura de Pantalla Aquí] | G19: Generado con ReportLab. Incluye nombre y NIT del negocio, fecha del reporte, tabla de ventas, totales con IVA y sello de generacion. Se pagina solo si el dia tiene muchas ventas. Las anuladas aparecen listadas pero no suman al total.
A20: REQ-06 | B20: Reportes y Facturación | C20: Exportación del reporte en Excel | D20: Exportar el reporte diario de ventas en formato Excel (.xlsx) con información organizada en columnas para posterior análisis, filtrado o procesamiento de datos. | E20: Cumplido | F20: [Pegar Captura de Pantalla Aquí] | G20: Generado con openpyxl. Tres hojas: Ventas, Detalle (una fila por articulo, para analizar) y Resumen. Trae autofiltro, primera fila congelada, formato de moneda y formulas =SUM() vivas, de modo que al filtrar los totales se recalculan solos.
A21: REQ-07 | B21: Reportes y Facturación | C21: Generación de facturas de venta | D21: El sistema deberá generar facturas de venta a partir de operaciones comerciales con número de factura, fecha, datos del cliente, productos/servicios, cantidad, precio unitario, subtotal, impuestos, total y estado. | E21: Cumplido | F21: [Pegar Captura de Pantalla Aquí] | G21: La factura nace de una venta registrada y lleva numero consecutivo (FV-2026-000061), fecha, datos del cliente, detalle con cantidad y precio unitario, subtotal, IVA y total. Copia los datos del cliente al emitirse: es un documento y no cambia despues.
A22: REQ-08 | B22: Reportes y Facturación | C22: Consulta de facturas | D22: Los usuarios autorizados podrán consultar las facturas generadas mediante criterios de búsqueda como número de factura, cliente o fecha. | E22: Cumplido | F22: [Pegar Captura de Pantalla Aquí] | G22: GET /api/facturas busca por numero de factura, nombre, documento o correo del cliente, rango de fechas y estado. El cliente ve unicamente las suyas, y el recorte lo hace FastAPI a partir del rol del token.
A23: REQ-09 | B23: Reportes y Facturación | C23: Descarga de facturas | D23: Implementar la generación o descarga de facturas comerciales en formato apropiado (preferiblemente PDF). | E23: Cumplido | F23: [Pegar Captura de Pantalla Aquí] | G23: GET /api/facturas/{id}/pdf entrega el documento con Content-Disposition. Se descarga desde el panel del administrador, desde el del empleado y desde el del propio cliente, que solo puede bajar las suyas.
A24: REQ-10 | B24: Dashboards y Analítica | C24: Dashboard administrativo | D24: Dashboard consolidado para el Administrador con indicadores en Cards sobre total usuarios, productos, servicios, ventas, facturación y PQR recibidas y pendientes. | E24: Cumplido | F24: [Pegar Captura de Pantalla Aquí] | G24: Tarjetas tipo Card con usuarios, catalogo, ventas del periodo, facturacion, ventas de hoy, acumulado del mes, valor del inventario y PQR recibidas con las que siguen sin cerrar.
A25: REQ-11 | B25: Dashboards y Analítica | C25: Dashboard de ventas | D25: Visualización analítica del comportamiento de ventas mediante gráfico de barras, gráfico lineal e indicadores numéricos en Cards por día, semana o mes. | E25: Cumplido | F25: [Pegar Captura de Pantalla Aquí] | G25: Grafico de barras y grafico lineal sobre la misma serie, mas los Cards de indicadores y los repartos por estado y forma de pago. Se puede agrupar por dia, semana o mes. Estan dibujados en SVG propio, sin sumar ninguna libreria al proyecto.
... A39: REQ-25 | B39: Pruebas & Evidencias | C39: Pruebas de Endpoints con Postman | D39: Demostración de pruebas funcionales mediante Postman (GET, POST, PUT, PATCH, DELETE) sobre los nuevos endpoints de ventas, facturas, PQR y chatbot IA. | E39: Cumplido | F39: [Pegar Captura de Pantalla Aquí] | G39: Coleccion de Postman con 84 peticiones en 12 carpetas (backend/postman/). Ademas, scripts/verificar_quinto_avance.py recorre la API contra MySQL real comprobando tanto lo que debe funcionar como lo que debe ser rechazado, y deja anuladas las ventas que crea. Se suman 130 pruebas automaticas con pytest.
A40: URL del Drive o GitHub del Entregable: | D40: https://github.com/tomascardonahincapie/motoshub-react-fastapi
A41: Versión del Instrumento: 2.0 | Quinto Entregable React + FastAPI + IA | Generado: 2026-09-14
A42: Nota: Este archivo es una herramienta de autoevaluación académica ajustada al Quinto Avance para el SENA ADSO Ficha 3406204.

Sheet Resumen por Categoría
A1: RESUMEN EJECUTIVO DE REQUERIMIENTOS POR CATEGORÍA
A3: Categoría / Módulo | B3: Total Requerimientos | C3: Cumplidos | D3: % Cumplimiento
A4: Módulo de Ventas | B4: =COUNTIF('Lista de Chequeo Q5'!B15:B39, "Módulo de Ventas") | C4: =COUNTIFS('Lista de Chequeo Q5'!B15:B39, "Módulo de Ventas", 'Lista de Chequeo Q5'!E15:E39, "Cumplido") | D4: =IF(B4>0, C4/B4, 0)
A5: Reportes y Facturación | B5: =COUNTIF('Lista de Chequeo Q5'!B15:B39, "Reportes y Facturación") | C5: =COUNTIFS('Lista de Chequeo Q5'!B15:B39, "Reportes y Facturación", 'Lista de Chequeo Q5'!E15:E39, "Cumplido") | D5: =IF(B5>0, C5/B5, 0)
A6: Dashboards y Analítica | B6: =COUNTIF('Lista de Chequeo Q5'!B15:B39, "Dashboards y Analítica") | C6: =COUNTIFS('Lista de Chequeo Q5'!B15:B39, "Dashboards y Analítica", 'Lista de Chequeo Q5'!E15:E39, "Cumplido") | D6: =IF(B6>0, C6/B6, 0)
A7: Backend FastAPI | B7: =COUNTIF('Lista de Chequeo Q5'!B15:B39, "Backend FastAPI") | C7: =COUNTIFS('Lista de Chequeo Q5'!B15:B39, "Backend FastAPI", 'Lista de Chequeo Q5'!E15:E39, "Cumplido") | D7: =IF(B7>0, C7/B7, 0)
A8: Backend & Frontend | B8: =COUNTIF('Lista de Chequeo Q5'!B15:B39, "Backend & Frontend") | C8: =COUNTIFS('Lista de Chequeo Q5'!B15:B39, "Backend & Frontend", 'Lista de Chequeo Q5'!E15:E39, "Cumplido") | D8: =IF(B8>0, C8/B8, 0)
A9: Módulo PQR | B9: =COUNTIF('Lista de Chequeo Q5'!B15:B39, "Módulo PQR") | C9: =COUNTIFS('Lista de Chequeo Q5'!B15:B39, "Módulo PQR", 'Lista de Chequeo Q5'!E15:E39, "Cumplido") | D9: =IF(B9>0, C9/B9, 0)
A10: Chatbot & IA | B10: =COUNTIF('Lista de Chequeo Q5'!B15:B39, "Chatbot & IA") | C10: =COUNTIFS('Lista de Chequeo Q5'!B15:B39, "Chatbot & IA", 'Lista de Chequeo Q5'!E15:E39, "Cumplido") | D10: =IF(B10>0, C10/B10, 0)
A11: Seguridad & Config | B11: =COUNTIF('Lista de Chequeo Q5'!B15:B39, "Seguridad & Config") | C11: =COUNTIFS('Lista de Chequeo Q5'!B15:B39, "Seguridad & Config", 'Lista de Chequeo Q5'!E15:E39, "Cumplido") | D11: =IF(B11>0, C11/B11, 0)
A12: Despliegue en la Nube | B12: =COUNTIF('Lista de Chequeo Q5'!B15:B39, "Despliegue en la Nube") | C12: =COUNTIFS('Lista de Chequeo Q5'!B15:B39, "Despliegue en la Nube", 'Lista de Chequeo Q5'!E15:E39, "Cumplido") | D12: =IF(B12>0, C12/B12, 0)
A13: Base de Datos SQL | B13: =COUNTIF('Lista de Chequeo Q5'!B15:B39, "Base de Datos SQL") | C13: =COUNTIFS('Lista de Chequeo Q5'!B15:B39, "Base de Datos SQL", 'Lista de Chequeo Q5'!E15:E39, "Cumplido") | D13: =IF(B13>0, C13/B13, 0)
A14: Frontend React | B14: =COUNTIF('Lista de Chequeo Q5'!B15:B39, "Frontend React") | C14: =COUNTIFS('Lista de Chequeo Q5'!B15:B39, "Frontend React", 'Lista de Chequeo Q5'!E15:E39, "Cumplido") | D14: =IF(B14>0, C14/B14, 0)
A15: Seguridad | B15: =COUNTIF('Lista de Chequeo Q5'!B15:B39, "Seguridad") | C15: =COUNTIFS('Lista de Chequeo Q5'!B15:B39, "Seguridad", 'Lista de Chequeo Q5'!E15:E39, "Cumplido") | D15: =IF(B15>0, C15/B15, 0)
A16: Pruebas & Evidencias | B16: =COUNTIF('Lista de Chequeo Q5'!B15:B39, "Pruebas & Evidencias") | C16: =COUNTIFS('Lista de Chequeo Q5'!B15:B39, "Pruebas & Evidencias", 'Lista de Chequeo Q5'!E15:E39, "Cumplido") | D16: =IF(B16>0, C16/B16, 0)
A17: Documentación | B17: =COUNTIF('Lista de Chequeo Q5'!B15:B39, "Documentación") | C17: =COUNTIFS('Lista de Chequeo Q5'!B15:B39, "Documentación", 'Lista de Chequeo Q5'!E15:E39, "Cumplido") | D17: =IF(B17>0, C17/B17, 0)
A18: TOTAL GENERAL | B18: =SUM(B4:B17) | C18: =SUM(C4:C17) | D18: =IF(B18>0, C18/B18, 0)
